<?xml version="1.0" encoding="utf-8"?>
<edit>
 <!--Generated for edit20-->
 <timestamp>
  09:51, 29 September 2014
 </timestamp>
 <prevtext>
  <line>
   | domesticpartner         = &lt;ahref&gt;Mark Speight&lt;/ahref&gt; &lt;small&gt;(2005–08; her death)&lt;/small&gt;
  </line>
  <line>
   }}
  </line>
  <line>
   ==Career==
  </line>
  <Minus>
   '''Natasha Louise Collins''' (7 September 1976 – 3 January 2008) was an &lt;ahref&gt;England|English&lt;/ahref&gt; &lt;ahref&gt;actress&lt;/ahref&gt; and &lt;ahref&gt;Model (person)|model&lt;/ahref&gt;, and the girlfriend of &lt;ahref&gt;Mark Speight&lt;/ahref&gt;. She died of a drug overdose and severe scolds in January 2008.
  </Minus>
  <Minus>
   '''Natasha Louise Collins''' (7 September 1976 – 3 January 2008) was an &lt;ahref&gt;England|English&lt;/ahref&gt; &lt;ahref&gt;actress&lt;/ahref&gt; and &lt;ahref&gt;Model (person)|model&lt;/ahref&gt;, and the girlfriend of &lt;ahref&gt;Mark Speight&lt;/ahref&gt;. She died of a drug overdose and severe scolds in January 2008.
  </Minus>
 </prevtext>
 <current_text>
  <lines>
   | domesticpartner         = &lt;ahref&gt;Mark Speight&lt;/ahref&gt; &lt;small&gt;(2005–08; her death)&lt;/small&gt;
  </lines>
  <lines>
   }}
  </lines>
  <lines>
   ==Career==
  </lines>
  <plus>
   '''Natasha Louise Collins''' (7 September 1976 – 3 January 2008) was an &lt;ahref&gt;England|English&lt;/ahref&gt; &lt;ahref&gt;actress&lt;/ahref&gt; and &lt;ahref&gt;Model (person)|model&lt;/ahref&gt;, and the girlfriend of &lt;ahref&gt;Mark Speight&lt;/ahref&gt;. She died of a drug overdose and severe scalds in January 2008.
  </plus>
  <plus>
   '''Natasha Louise Collins''' (7 September 1976 – 3 January 2008) was an &lt;ahref&gt;England|English&lt;/ahref&gt; &lt;ahref&gt;actress&lt;/ahref&gt; and &lt;ahref&gt;Model (person)|model&lt;/ahref&gt;, and the girlfriend of &lt;ahref&gt;Mark Speight&lt;/ahref&gt;. She died of a drug overdose and severe scalds in January 2008.
  </plus>
 </current_text>
</edit>